filminline/__init__.py
filminline/cli.py
filminline/filminline.py
filminline-0.0.2.dist-info/METADATA
filminline-0.0.2.dist-info/WHEEL
filminline-0.0.2.dist-info/entry_points.txt
filminline-0.0.2.dist-info/top_level.txt
filminline-0.0.2.dist-info/RECORD
